setup.py
cellh5/__init__.py
cellh5/cellh5.py
cellh5/cellh5write.py
cellh5.egg-info/PKG-INFO
cellh5.egg-info/SOURCES.txt
cellh5.egg-info/dependency_links.txt
cellh5.egg-info/entry_points.txt
cellh5.egg-info/requires.txt
cellh5.egg-info/top_level.txt
cellh5/hmm_wrapper/__init__.py