Metadata-Version: 1.1
Name: cellh5
Version: 1.3.0
Summary: A format for data exchange in high-content screening
Home-page: http://cellh5.org
Author: Christoph Sommer, Rudolf Hoefler
Author-email: christoph.sommer@imba.oeaw.ac.at, rudolf.hoefler@gmail.com
License: LGPL
Platform: UNKNOWN
Classifier: Development Status :: 5 - Production/Stable
Classifier: Intended Audience :: Science/Research
Classifier: License :: OSI Approved :: GNU Library or Lesser General Public License (LGPL)
Classifier: Operating System :: OS Independent
Classifier: Programming Language :: C
Classifier: Programming Language :: C++
Classifier: Programming Language :: Cython
Classifier: Programming Language :: Python :: 2
Classifier: Programming Language :: Python :: 2.6
Classifier: Programming Language :: Python :: 2.7
Classifier: Topic :: Scientific/Engineering :: Bio-Informatics
Classifier: Topic :: Scientific/Engineering
